{
	"version": "suncg@1.0.0",
	"id": "052",
	"up": [
		0,
		1,
		0
	],
	"front": [
		0,
		0,
		1
	],
	"scaleToMeters": 1,
	"levels": [
		{
			"id": "0",
			"bbox": {
				"min": [
					0,
					0,
					0
				],
				"max": [
					4,
					2.4,
					6
				]
			},
			"nodes": [
				{
					"id": "0_0",
					"type": "Room",
					"valid": 1,
					"modelId": "fr_0rm_0",
					"nodeIndices": [
						1,
						2,
						3,
						4,
						5,
						6
					],
					"transform": [
						0.769923386972124,
						0,
						0,
						0,
						0,
						0.875912463142925,
						0,
						0,
						0,
						0,
						1.15940147202884,
						0,
						-29.5264737533147,
						0,
						-43.4081222864036,
						1
					],
					"roomTypes": [
						"Bedroom"
					],
					"bbox": {
						"min": [
							0,
							0,
							0
						],
						"max": [
							4,
							2.4,
							6
						]
					}
				},
				{
					"id": "0_1",
					"type": "Object",
					"valid": 1,
					"modelId": "3df20e86818847dcd054cd3079273293",
					"transform": [
						-1.00000005227221,
						0,
						-1.22460641783526e-16,
						0,
						0,
						1.00000005227221,
						0,
						0,
						1.22460641783526e-16,
						0,
						-1.00000005227221,
						0,
						2.40264862060547,
						0,
						4.96520034790039,
						1
					],
					"bbox": {
						"min": [
							1.73008758544922,
							0,
							3.9776432962786
						],
						"max": [
							3.07520965576172,
							1.31324806864638,
							5.95275739952218
						]
					},
					"materials": [
						{
							"name": "color",
							"diffuse": "#a3a3a3"
						},
						{
							"name": "color_1",
							"diffuse": "#6990a3"
						}
					]
				},
				{
					"id": "0_2",
					"type": "Object",
					"valid": 1,
					"modelId": "849c1f116afb9875850130934a5671bf",
					"transform": [
						-1.33158050632024e-07,
						0,
						-0.999999972458328,
						0,
						0,
						0.999999972458337,
						0,
						0,
						0.999999972458328,
						0,
						-1.33158050632024e-07,
						0,
						0.467273559570313,
						0,
						5.4490446472168,
						1
					],
					"bbox": {
						"min": [
							-0.00697242736816406,
							0,
							5.03458965863158
						],
						"max": [
							0.941519546508789,
							1.12915696890114,
							5.86349963580202
						]
					},
					"materials": [
						{
							"name": "color",
							"diffuse": "#a3a3a3"
						},
						{
							"name": "color_1",
							"diffuse": "#6990a3"
						}
					]
				},
				{
					"id": "0_3",
					"type": "Object",
					"valid": 1,
					"modelId": "65f9103ab7a64e83cb7105765410e2d6",
					"transform": [
						-2.66316103044813e-07,
						0,
						-0.999999978081287,
						0,
						0,
						0.999999978081322,
						0,
						0,
						0.999999978081287,
						0,
						-2.66316103044813e-07,
						0,
						0.487157745361328,
						0,
						2.42667873382568,
						1
					],
					"bbox": {
						"min": [
							-0.0530582427978516,
							0,
							2.0242177426471
						],
						"max": [
							1.02737373352051,
							0.9291709796338,
							2.82913972500427
						]
					},
					"materials": [
						{
							"name": "color",
							"diffuse": "#a3a3a3"
						},
						{
							"name": "color_1",
							"diffuse": "#6990a3"
						}
					]
				},
				{
					"id": "0_4",
					"type": "Object",
					"valid": 1,
					"modelId": "2bc37c326782ecfb9bbc8ad5ece3c1b",
					"transform": [
						-1.00000003222732,
						0,
						-1.22460639328816e-16,
						0,
						0,
						1.00000003222732,
						0,
						0,
						1.22460639328816e-16,
						0,
						-1.00000003222732,
						0,
						3.39021942138672,
						0,
						5.64125610351562,
						1
					],
					"bbox": {
						"min": [
							3.13833141326904,
							0,
							5.3435760939222
						],
						"max": [
							3.64210742950439,
							0.704807022714042,
							5.93893611310905
						]
					},
					"materials": [
						{
							"name": "color",
							"diffuse": "#a3a3a3"
						},
						{
							"name": "color_1",
							"diffuse": "#6990a3"
						}
					]
				},
				{
					"id": "0_5",
					"type": "Object",
					"valid": 1,
					"modelId": "3c693492780885e248af20241edfd17b",
					"transform": [
						5.32632222131255e-07,
						0,
						1.00000000785399,
						0,
						0,
						1.00000000785413,
						0,
						0,
						-1.00000000785399,
						0,
						5.32632222131255e-07,
						0,
						3.61640441894531,
						0,
						1.2137548828125,
						1
					],
					"bbox": {
						"min": [
							3.17345241546631,
							0,
							0.948235880727079
						],
						"max": [
							4.05935642242432,
							1.76174101383695,
							1.47927388489792
						]
					},
					"materials": [
						{
							"name": "color",
							"diffuse": "#a3a3a3"
						},
						{
							"name": "color_1",
							"diffuse": "#6990a3"
						}
					]
				},
				{
					"id": "0_6",
					"type": "Object",
					"valid": 1,
					"modelId": "119ddb219f69b1cc492d9da2668ec34c",
					"transform": [
						5.32632226597841e-07,
						0,
						1.00000001623986,
						0,
						0,
						1.00000001624,
						0,
						0,
						-1.00000001623986,
						0,
						5.32632226597841e-07,
						0,
						1.30902893066406,
						0,
						2.42667873382568,
						1
					],
					"bbox": {
						"min": [
							0.99332992553711,
							0,
							2.09832272849318
						],
						"max": [
							1.62472793579102,
							0.970646015763295,
							2.75503473915819
						]
					},
					"materials": [
						{
							"name": "color",
							"diffuse": "#a3a3a3"
						},
						{
							"name": "color_1",
							"diffuse": "#6990a3"
						}
					]
				}
			]
		}
	],
	"bbox": {
		"min": [
			0,
			0,
			0
		],
		"max": [
			4,
			2.4,
			6
		]
	}
}