{
	"version": "suncg@1.0.0",
	"id": "050",
	"up": [
		0,
		1,
		0
	],
	"front": [
		0,
		0,
		1
	],
	"scaleToMeters": 1,
	"levels": [
		{
			"id": "0",
			"bbox": {
				"min": [
					0,
					0,
					0
				],
				"max": [
					4,
					2.4,
					6
				]
			},
			"nodes": [
				{
					"id": "0_0",
					"type": "Room",
					"valid": 1,
					"modelId": "fr_0rm_0",
					"nodeIndices": [
						1,
						2,
						3,
						4,
						5,
						6,
						7,
						8,
						9,
						10
					],
					"transform": [
						0.769923386972124,
						0,
						0,
						0,
						0,
						0.875912463142925,
						0,
						0,
						0,
						0,
						1.15940147202884,
						0,
						-29.5264737533147,
						0,
						-43.4081222864036,
						1
					],
					"roomTypes": [
						"Bedroom"
					],
					"bbox": {
						"min": [
							0,
							0,
							0
						],
						"max": [
							4,
							2.4,
							6
						]
					}
				},
				{
					"id": "0_1",
					"type": "Object",
					"valid": 1,
					"modelId": "65f9103ab7a64e83cb7105765410e2d6",
					"transform": [
						5.32632206273297e-07,
						0,
						0.99999997808118,
						0,
						0,
						0.999999978081322,
						0,
						0,
						-0.99999997808118,
						0,
						5.32632206273297e-07,
						0,
						3.51535247802734,
						0,
						1.71748306274414,
						1
					],
					"bbox": {
						"min": [
							2.97513648986816,
							0,
							1.31502207156555
						],
						"max": [
							4.05556846618652,
							0.9291709796338,
							2.11994405392273
						]
					},
					"materials": [
						{
							"name": "color",
							"diffuse": "#a3a3a3"
						},
						{
							"name": "color_1",
							"diffuse": "#6990a3"
						}
					]
				},
				{
					"id": "0_2",
					"type": "Object",
					"valid": 1,
					"modelId": "3225898a2fe3f6257ed90bca788562eb",
					"transform": [
						-2.66316102865213e-07,
						0,
						-0.999999977406903,
						0,
						0,
						0.999999977406938,
						0,
						0,
						0.999999977406903,
						0,
						-2.66316102865213e-07,
						0,
						2.76056030273437,
						0,
						1.70422714233398,
						1
					],
					"bbox": {
						"min": [
							2.40936531066895,
							0,
							1.36871814991416
						],
						"max": [
							3.1117552947998,
							0.9097969794449,
							2.03973613475381
						]
					},
					"materials": [
						{
							"name": "color",
							"diffuse": "#a3a3a3"
						},
						{
							"name": "color_1",
							"diffuse": "#6990a3"
						}
					]
				},
				{
					"id": "0_3",
					"type": "Object",
					"valid": 1,
					"modelId": "30b6b75548448c5f88a441c3f24d213a",
					"transform": [
						5.32632193598438e-07,
						0,
						0.999999954284536,
						0,
						0,
						0.999999954284678,
						0,
						0,
						-0.999999954284536,
						0,
						5.32632193598438e-07,
						0,
						2.813583984375,
						0,
						4.52775299072266,
						1
					],
					"bbox": {
						"min": [
							1.98047302246094,
							0,
							3.43265704078532
						],
						"max": [
							3.64669494628906,
							1.01650095353033,
							5.62284894065999
						]
					},
					"materials": [
						{
							"name": "color",
							"diffuse": "#a3a3a3"
						},
						{
							"name": "color_1",
							"diffuse": "#6990a3"
						}
					]
				},
				{
					"id": "0_4",
					"type": "Object",
					"valid": 1,
					"modelId": "653776d3f5cf198ccf004563556ddb36",
					"transform": [
						-1,
						0,
						-1.22460635382238e-16,
						0,
						0,
						1,
						0,
						0,
						1.22460635382238e-16,
						0,
						-1,
						0,
						0.347969665527344,
						0,
						2.47307472229004,
						1
					],
					"bbox": {
						"min": [
							0.112969665527344,
							0,
							2.23807472229004
						],
						"max": [
							0.582969665527344,
							1.799999,
							2.70807472229004
						]
					},
					"materials": [
						{
							"name": "color",
							"diffuse": "#a3a3a3"
						},
						{
							"name": "color_1",
							"diffuse": "#6990a3"
						}
					]
				},
				{
					"id": "0_5",
					"type": "Object",
					"valid": 1,
					"modelId": "bde984cab54f1b8fce58f346b4d8abe",
					"transform": [
						5.32632226000048e-07,
						0,
						1.00000001511753,
						0,
						0,
						1.00000001511767,
						0,
						0,
						-1.00000001511753,
						0,
						5.32632226000048e-07,
						0,
						3.73487548828125,
						0,
						5.70090789794922,
						1
					],
					"bbox": {
						"min": [
							3.50878448486328,
							0,
							5.56161989584351
						],
						"max": [
							3.96096649169922,
							0.456220006896983,
							5.84019590005493
						]
					},
					"materials": [
						{
							"name": "color",
							"diffuse": "#a3a3a3"
						},
						{
							"name": "color_1",
							"diffuse": "#6990a3"
						}
					]
				},
				{
					"id": "0_6",
					"type": "Object",
					"valid": 1,
					"modelId": "bde984cab54f1b8fce58f346b4d8abe",
					"transform": [
						5.32632226000048e-07,
						0,
						1.00000001511753,
						0,
						0,
						1.00000001511767,
						0,
						0,
						-1.00000001511753,
						0,
						5.32632226000048e-07,
						0,
						3.71499145507812,
						0,
						3.36785400390625,
						1
					],
					"bbox": {
						"min": [
							3.48890045166016,
							0,
							3.22856600180054
						],
						"max": [
							3.94108245849609,
							0.456220006896983,
							3.50714200601196
						]
					},
					"materials": [
						{
							"name": "color",
							"diffuse": "#a3a3a3"
						},
						{
							"name": "color_1",
							"diffuse": "#6990a3"
						}
					]
				},
				{
					"id": "0_7",
					"type": "Object",
					"valid": 1,
					"modelId": "3c693492780885e248af20241edfd17b",
					"transform": [
						-1.3315805534526e-07,
						0,
						-1.00000000785412,
						0,
						0,
						1.00000000785413,
						0,
						0,
						1.00000000785412,
						0,
						-1.3315805534526e-07,
						0,
						0.321457977294922,
						0,
						5.47555618286133,
						1
					],
					"bbox": {
						"min": [
							-0.121494026184082,
							0,
							5.21003718077591
						],
						"max": [
							0.764409980773926,
							1.76174101383695,
							5.74107518494675
						]
					},
					"materials": [
						{
							"name": "color",
							"diffuse": "#a3a3a3"
						},
						{
							"name": "color_1",
							"diffuse": "#6990a3"
						}
					]
				},
				{
					"id": "0_8",
					"type": "Object",
					"valid": 1,
					"modelId": "750ba8feafceba921933ffef19678834",
					"transform": [
						-1.33158053266139e-07,
						0,
						-0.999999992240196,
						0,
						0,
						0.999999992240205,
						0,
						0,
						0.999999992240196,
						0,
						-1.33158053266139e-07,
						0,
						0.215410003662109,
						0,
						4.68019638061523,
						1
					],
					"bbox": {
						"min": [
							-0.0362879943847656,
							0,
							4.58187638137818
						],
						"max": [
							0.467108001708984,
							1.22702899047851,
							4.77851637985229
						]
					},
					"materials": [
						{
							"name": "color",
							"diffuse": "#a3a3a3"
						},
						{
							"name": "color_1",
							"diffuse": "#6990a3"
						}
					]
				},
				{
					"id": "0_9",
					"type": "Object",
					"valid": 1,
					"modelId": "eb5b11f0820f73acc5d9967b65588a28",
					"transform": [
						-2.66316115051301e-07,
						0,
						-1.00000002316489,
						0,
						0,
						1.00000002316492,
						0,
						0,
						1.00000002316489,
						0,
						-2.66316115051301e-07,
						0,
						0.646229553222656,
						0,
						1.14084747314453,
						1
					],
					"bbox": {
						"min": [
							-0.349728469848633,
							0,
							0.576473460070852
						],
						"max": [
							1.64218757629395,
							2.8772080666503,
							1.70522148621821
						]
					},
					"materials": [
						{
							"name": "color",
							"diffuse": "#a3a3a3"
						},
						{
							"name": "color_1",
							"diffuse": "#6990a3"
						}
					]
				},
				{
					"id": "0_10",
					"type": "Object",
					"valid": 1,
					"modelId": "951cc2a069d075cdadaabe1b581f21e1",
					"transform": [
						5.32632209781808e-07,
						0,
						0.999999984668297,
						0,
						0,
						0.999999984668439,
						0,
						0,
						-0.999999984668297,
						0,
						5.32632209781808e-07,
						0,
						1.56752105712891,
						0,
						1.06131164550781,
						1
					],
					"bbox": {
						"min": [
							1.28088806152344,
							0,
							0.752555650241524
						],
						"max": [
							1.85415405273437,
							0.987452984860804,
							1.3700676407741
						]
					},
					"materials": [
						{
							"name": "color",
							"diffuse": "#a3a3a3"
						},
						{
							"name": "color_1",
							"diffuse": "#6990a3"
						}
					]
				}
			]
		}
	],
	"bbox": {
		"min": [
			0,
			0,
			0
		],
		"max": [
			4,
			2.4,
			6
		]
	}
}